grid3d_maps/__init__.py
grid3d_maps/version.py
grid3d_maps/avghc/__init__.py
grid3d_maps/avghc/_compute_avg.py
grid3d_maps/avghc/_compute_hcpfz.py
grid3d_maps/avghc/_configparser.py
grid3d_maps/avghc/_export_via_fmudataio.py
grid3d_maps/avghc/_get_grid_props.py
grid3d_maps/avghc/_get_zonation_filters.py
grid3d_maps/avghc/_hc_plotmap.py
grid3d_maps/avghc/_loader.py
grid3d_maps/avghc/_mapsettings.py
grid3d_maps/avghc/grid3d_average_map.py
grid3d_maps/avghc/grid3d_hc_thickness.py
grid3d_maps/contact/__init__.py
grid3d_maps/contact/_compute_contact.py
grid3d_maps/contact/_get_grid_props.py
grid3d_maps/contact/grid3d_contact_map.py
grid3d_maps/forward_models/__init__.py
grid3d_maps/forward_models/grid3d_average_map.py
grid3d_maps/forward_models/grid3d_hc_thickness.py
grid3d_maps/hook_implementations/jobs.py
grid3d_maps-1.11.0.dist-info/licenses/AUTHORS.rst
grid3d_maps-1.11.0.dist-info/licenses/LICENSE
grid3d_maps-1.11.0.dist-info/METADATA
grid3d_maps-1.11.0.dist-info/WHEEL
grid3d_maps-1.11.0.dist-info/entry_points.txt
grid3d_maps-1.11.0.dist-info/top_level.txt
grid3d_maps-1.11.0.dist-info/RECORD
