Metadata-Version: 2.4
Name: grid3d_maps
Version: 1.11.0
Summary: Make HC thickness, avg maps, etc directly from 3D props
Author-email: Equinor <fg_fmu-atlas@equinor.com>
License:                     GNU GENERAL PUBLIC LICENSE
Project-URL: Homepage, https://github.com/equinor/grid3d-maps
Project-URL: Repository, https://github.com/equinor/grid3d-maps
Project-URL: Documentation, https://equinor.github.io/grid3d-maps
Keywords: energy,subsurface,reservoir,scientific,engineering,maps,xtgeo
Classifier: Development Status :: 5 - Production/Stable
Classifier: Intended Audience :: Science/Research
Classifier: Topic :: Scientific/Engineering
Classifier: Topic :: Scientific/Engineering :: Physics
Classifier: Topic :: Software Development :: Libraries
Classifier: Topic :: Utilities
Classifier: Operating System :: POSIX :: Linux
Classifier: Operating System :: Microsoft :: Windows
Classifier: Operating System :: MacOS
Classifier: Programming Language :: Python :: 3.11
Classifier: Programming Language :: Python :: 3.12
Classifier: Programming Language :: Python :: 3.13
Classifier: Natural Language :: English
Classifier: License :: OSI Approved :: GNU General Public License v3 (GPLv3)
Requires-Python: >=3.11
License-File: LICENSE
License-File: AUTHORS.rst
Requires-Dist: fmu-config
Requires-Dist: fmu-dataio>=1.3.0
Requires-Dist: numpy
Requires-Dist: pyyaml
Requires-Dist: xtgeo>=2.20.7
Requires-Dist: xtgeoviz
Provides-Extra: tests
Requires-Dist: coverage>=4.1; extra == "tests"
Requires-Dist: ert; sys_platform != "win32" and extra == "tests"
Requires-Dist: ruff; extra == "tests"
Requires-Dist: mypy; extra == "tests"
Requires-Dist: pylint; extra == "tests"
Requires-Dist: pytest; extra == "tests"
Requires-Dist: pytest-cov; extra == "tests"
Requires-Dist: pytest-runner; extra == "tests"
Requires-Dist: pytest-xdist; extra == "tests"
Requires-Dist: rstcheck; extra == "tests"
Requires-Dist: types-PyYAML; extra == "tests"
Provides-Extra: docs
Requires-Dist: myst-parser; extra == "docs"
Requires-Dist: sphinx; extra == "docs"
Requires-Dist: sphinx-argparse; extra == "docs"
Requires-Dist: sphinx-autodoc-typehints<3.6; extra == "docs"
Requires-Dist: sphinx-copybutton; extra == "docs"
Requires-Dist: sphinx-togglebutton; extra == "docs"
Requires-Dist: sphinx_rtd_theme; extra == "docs"
Dynamic: license-file
